safekeylab/__init__.py
safekeylab/client.py
safekeylab/exceptions.py
safekeylab/protector.py
safekeylab/scanner.py
safekeylab-1.1.1.dist-info/METADATA
safekeylab-1.1.1.dist-info/WHEEL
safekeylab-1.1.1.dist-info/entry_points.txt
safekeylab-1.1.1.dist-info/top_level.txt
safekeylab-1.1.1.dist-info/RECORD
